static_fire_toolkit/__init__.py
static_fire_toolkit/__main__.py
static_fire_toolkit/cli.py
static_fire_toolkit/config_loader.py
static_fire_toolkit/hanaro_standard_stylesheet.mplstyle
static_fire_toolkit/style.py
static_fire_toolkit/burnrate_calc/analyze_burnrate.py
static_fire_toolkit/post_process/pressure_post_processing.py
static_fire_toolkit/post_process/thrust_post_processing.py
static_fire_toolkit-1.0.1.dist-info/licenses/LICENSE
static_fire_toolkit-1.0.1.dist-info/METADATA
static_fire_toolkit-1.0.1.dist-info/WHEEL
static_fire_toolkit-1.0.1.dist-info/entry_points.txt
static_fire_toolkit-1.0.1.dist-info/top_level.txt
static_fire_toolkit-1.0.1.dist-info/RECORD
