Metadata-Version: 2.4
Name: static-fire-toolkit
Version: 1.0.1
Summary: Command-line toolkit for static-fire test data processing and analysis
Author-email: SNU Rocket Team HANARO <hanarodrive@gmail.com>
Maintainer-email: Yunseo Kim <yunseo@snu.ac.kr>
License: MIT
Project-URL: Homepage, https://github.com/snu-hanaro/static-fire-toolkit
Project-URL: Source, https://github.com/snu-hanaro/static-fire-toolkit
Project-URL: Changelog, https://github.com/snu-hanaro/static-fire-toolkit/blob/main/docs/CHANGELOG.md
Project-URL: Issues, https://github.com/snu-hanaro/static-fire-toolkit/issues
Project-URL: Release Notes, https://github.com/snu-hanaro/static-fire-toolkit/releases
Project-URL: About HANARO, https://hanaro.snu.ac.kr/
Keywords: rocket,rocketry,static-fire,thrust,pressure,data-processing,hanaro,snu
Classifier: Environment :: Console
Classifier: Intended Audience :: Science/Research
Classifier: License :: OSI Approved :: MIT License
Classifier: Operating System :: OS Independent
Classifier: Programming Language :: Python
Classifier: Programming Language :: Python :: 3
Classifier: Programming Language :: Python :: 3 :: Only
Classifier: Programming Language :: Python :: 3.10
Classifier: Programming Language :: Python :: 3.11
Classifier: Programming Language :: Python :: 3.12
Classifier: Programming Language :: Python :: 3.13
Classifier: Topic :: Scientific/Engineering
Classifier: Topic :: Scientific/Engineering :: Information Analysis
Classifier: Topic :: Scientific/Engineering :: Physics
Classifier: Topic :: Scientific/Engineering :: Visualization
Classifier: Topic :: Software Development :: Libraries
Classifier: Topic :: Software Development :: Libraries :: Python Modules
Requires-Python: >=3.10
License-File: LICENSE
Requires-Dist: numpy>=2.0
Requires-Dist: pandas>=2.0
Requires-Dist: scipy>=1.10
Requires-Dist: matplotlib>=3.10
Requires-Dist: openpyxl>=3.1
Dynamic: license-file
